evalview/__init__.py
evalview/chat.py
evalview/cli.py
evalview/expander.py
evalview/recorder.py
evalview/adapters/__init__.py
evalview/adapters/anthropic_adapter.py
evalview/adapters/base.py
evalview/adapters/crewai_adapter.py
evalview/adapters/goose_adapter.py
evalview/adapters/http_adapter.py
evalview/adapters/huggingface_adapter.py
evalview/adapters/langgraph_adapter.py
evalview/adapters/mcp_adapter.py
evalview/adapters/ollama_adapter.py
evalview/adapters/openai_assistants_adapter.py
evalview/adapters/registry.py
evalview/adapters/tapescope_adapter.py
evalview/ci/__init__.py
evalview/ci/comment.py
evalview/core/__init__.py
evalview/core/config.py
evalview/core/diff.py
evalview/core/golden.py
evalview/core/llm_provider.py
evalview/core/loader.py
evalview/core/parallel.py
evalview/core/pricing.py
evalview/core/retry.py
evalview/core/security.py
evalview/core/tool_categories.py
evalview/core/tracing.py
evalview/core/types.py
evalview/core/watcher.py
evalview/evaluators/__init__.py
evalview/evaluators/cost_evaluator.py
evalview/evaluators/evaluator.py
evalview/evaluators/hallucination_evaluator.py
evalview/evaluators/latency_evaluator.py
evalview/evaluators/output_evaluator.py
evalview/evaluators/safety_evaluator.py
evalview/evaluators/sequence_evaluator.py
evalview/evaluators/statistical_evaluator.py
evalview/evaluators/tool_call_evaluator.py
evalview/exporters/__init__.py
evalview/exporters/html_exporter.py
evalview/reporters/__init__.py
evalview/reporters/console_reporter.py
evalview/reporters/html_reporter.py
evalview/reporters/json_reporter.py
evalview/reporters/trace_live_reporter.py
evalview/reporters/trace_reporter.py
evalview/skills/__init__.py
evalview/skills/parser.py
evalview/skills/runner.py
evalview/skills/types.py
evalview/skills/validator.py
evalview/storage/__init__.py
evalview/storage/database.py
evalview/telemetry/__init__.py
evalview/telemetry/client.py
evalview/telemetry/config.py
evalview/telemetry/decorators.py
evalview/telemetry/events.py
evalview-0.2.3.dist-info/licenses/LICENSE
evalview-0.2.3.dist-info/licenses/NOTICE
evalview-0.2.3.dist-info/METADATA
evalview-0.2.3.dist-info/WHEEL
evalview-0.2.3.dist-info/entry_points.txt
evalview-0.2.3.dist-info/top_level.txt
evalview-0.2.3.dist-info/RECORD
