Metadata-Version: 2.4
Name: evalview
Version: 0.2.3
Summary: Pytest-style testing framework for AI agents — LangGraph, CrewAI, OpenAI, Anthropic
Author-email: EvalView Team <hidai@evalview.com>
License-Expression: Apache-2.0
Project-URL: Homepage, https://github.com/hidai25/eval-view
Project-URL: Documentation, https://github.com/hidai25/eval-view#readme
Project-URL: Repository, https://github.com/hidai25/eval-view.git
Project-URL: Issue Tracker, https://github.com/hidai25/eval-view/issues
Project-URL: Changelog, https://github.com/hidai25/eval-view/blob/main/CHANGELOG.md
Keywords: ai,agents,testing,evaluation,llm,langchain,langgraph,crewai,openai,anthropic,claude,pytest-ai,ai-agent-testing,llm-testing,agent-evaluation,regression-testing,ci-cd-testing,yaml-testing,tool-calling
Classifier: Development Status :: 4 - Beta
Classifier: Intended Audience :: Developers
Classifier: Programming Language :: Python :: 3
Classifier: Programming Language :: Python :: 3.9
Classifier: Programming Language :: Python :: 3.10
Classifier: Programming Language :: Python :: 3.11
Classifier: Programming Language :: Python :: 3.12
Classifier: Topic :: Software Development :: Testing
Classifier: Topic :: Software Development :: Quality Assurance
Classifier: Topic :: Scientific/Engineering :: Artificial Intelligence
Requires-Python: >=3.9
License-File: LICENSE
License-File: NOTICE
Requires-Dist: click>=8.1.0
Requires-Dist: pydantic>=2.5.0
Requires-Dist: pyyaml>=6.0
Requires-Dist: openai>=1.12.0
Requires-Dist: anthropic>=0.39.0
Requires-Dist: rich>=13.7.0
Requires-Dist: prompt_toolkit>=3.0.0
Requires-Dist: httpx>=0.26.0
Requires-Dist: python-dateutil>=2.8.2
Requires-Dist: python-dotenv>=1.0.0
Provides-Extra: reports
Requires-Dist: jinja2>=3.0; extra == "reports"
Requires-Dist: plotly>=5.0; extra == "reports"
Provides-Extra: watch
Requires-Dist: watchdog>=3.0; extra == "watch"
Provides-Extra: telemetry
Requires-Dist: posthog>=3.0.0; extra == "telemetry"
Provides-Extra: all
Requires-Dist: jinja2>=3.0; extra == "all"
Requires-Dist: plotly>=5.0; extra == "all"
Requires-Dist: watchdog>=3.0; extra == "all"
Requires-Dist: posthog>=3.0.0; extra == "all"
Provides-Extra: dev
Requires-Dist: pytest>=7.4.0; extra == "dev"
Requires-Dist: pytest-asyncio>=0.21.0; extra == "dev"
Requires-Dist: pytest-cov>=4.1.0; extra == "dev"
Requires-Dist: black==24.10.0; extra == "dev"
Requires-Dist: mypy>=1.7.0; extra == "dev"
Requires-Dist: ruff>=0.1.0; extra == "dev"
Requires-Dist: jinja2>=3.0; extra == "dev"
Requires-Dist: plotly>=5.0; extra == "dev"
Requires-Dist: watchdog>=3.0; extra == "dev"
Requires-Dist: anthropic>=0.39.0; extra == "dev"
Requires-Dist: fastapi>=0.109.0; extra == "dev"
Requires-Dist: uvicorn>=0.27.0; extra == "dev"
Dynamic: license-file
